{
  "version": "1.0",
  "defaultProvider": "cdnjs",
  "libraries": [
    {
      "library": "highlight.js@11.9.0",
      "destination": "wwwroot/lib/highlight.js/",
      "files": [
        "highlight.min.js",
        "es/languages/1c.min.js",
        "es/languages/abnf.min.js",
        "es/languages/accesslog.min.js",
        "es/languages/actionscript.min.js",
        "es/languages/ada.min.js",
        "es/languages/angelscript.min.js",
        "es/languages/apache.min.js",
        "es/languages/applescript.min.js",
        "es/languages/arcade.min.js",
        "es/languages/arduino.min.js",
        "es/languages/armasm.min.js",
        "es/languages/asciidoc.min.js",
        "es/languages/aspectj.min.js",
        "es/languages/autohotkey.min.js",
        "es/languages/autoit.min.js",
        "es/languages/avrasm.min.js",
        "es/languages/awk.min.js",
        "es/languages/axapta.min.js",
        "es/languages/bash.min.js",
        "es/languages/basic.min.js",
        "es/languages/bnf.min.js",
        "es/languages/brainfuck.min.js",
        "es/languages/c.min.js",
        "es/languages/cal.min.js",
        "es/languages/capnproto.min.js",
        "es/languages/ceylon.min.js",
        "es/languages/clean.min.js",
        "es/languages/clojure-repl.min.js",
        "es/languages/clojure.min.js",
        "es/languages/cmake.min.js",
        "es/languages/coffeescript.min.js",
        "es/languages/coq.min.js",
        "es/languages/cos.min.js",
        "es/languages/cpp.min.js",
        "es/languages/crmsh.min.js",
        "es/languages/crystal.min.js",
        "es/languages/csharp.min.js",
        "es/languages/csp.min.js",
        "es/languages/css.min.js",
        "es/languages/d.min.js",
        "es/languages/dart.min.js",
        "es/languages/delphi.min.js",
        "es/languages/diff.min.js",
        "es/languages/django.min.js",
        "es/languages/dns.min.js",
        "es/languages/dockerfile.min.js",
        "es/languages/dos.min.js",
        "es/languages/dsconfig.min.js",
        "es/languages/dts.min.js",
        "es/languages/dust.min.js",
        "es/languages/ebnf.min.js",
        "es/languages/elixir.min.js",
        "es/languages/elm.min.js",
        "es/languages/erb.min.js",
        "es/languages/erlang-repl.min.js",
        "es/languages/erlang.min.js",
        "es/languages/excel.min.js",
        "es/languages/fix.min.js",
        "es/languages/flix.min.js",
        "es/languages/fortran.min.js",
        "es/languages/fsharp.min.js",
        "es/languages/gams.min.js",
        "es/languages/gauss.min.js",
        "es/languages/gcode.min.js",
        "es/languages/gherkin.min.js",
        "es/languages/glsl.min.js",
        "es/languages/gml.min.js",
        "es/languages/go.min.js",
        "es/languages/golo.min.js",
        "es/languages/gradle.min.js",
        "es/languages/graphql.min.js",
        "es/languages/groovy.min.js",
        "es/languages/haml.min.js",
        "es/languages/handlebars.min.js",
        "es/languages/haskell.min.js",
        "es/languages/haxe.min.js",
        "es/languages/hsp.min.js",
        "es/languages/http.min.js",
        "es/languages/hy.min.js",
        "es/languages/inform7.min.js",
        "es/languages/ini.min.js",
        "es/languages/irpf90.min.js",
        "es/languages/isbl.min.js",
        "es/languages/java.min.js",
        "es/languages/javascript.min.js",
        "es/languages/jboss-cli.min.js",
        "es/languages/json.min.js",
        "es/languages/julia-repl.min.js",
        "es/languages/julia.min.js",
        "es/languages/kotlin.min.js",
        "es/languages/lasso.min.js",
        "es/languages/latex.min.js",
        "es/languages/ldif.min.js",
        "es/languages/leaf.min.js",
        "es/languages/less.min.js",
        "es/languages/lisp.min.js",
        "es/languages/livecodeserver.min.js",
        "es/languages/livescript.min.js",
        "es/languages/llvm.min.js",
        "es/languages/lsl.min.js",
        "es/languages/lua.min.js",
        "es/languages/makefile.min.js",
        "es/languages/markdown.min.js",
        "es/languages/mathematica.min.js",
        "es/languages/matlab.min.js",
        "es/languages/maxima.min.js",
        "es/languages/mel.min.js",
        "es/languages/mercury.min.js",
        "es/languages/mipsasm.min.js",
        "es/languages/mizar.min.js",
        "es/languages/mojolicious.min.js",
        "es/languages/monkey.min.js",
        "es/languages/moonscript.min.js",
        "es/languages/n1ql.min.js",
        "es/languages/nestedtext.min.js",
        "es/languages/nginx.min.js",
        "es/languages/nim.min.js",
        "es/languages/nix.min.js",
        "es/languages/node-repl.min.js",
        "es/languages/nsis.min.js",
        "es/languages/objectivec.min.js",
        "es/languages/ocaml.min.js",
        "es/languages/openscad.min.js",
        "es/languages/oxygene.min.js",
        "es/languages/parser3.min.js",
        "es/languages/perl.min.js",
        "es/languages/pf.min.js",
        "es/languages/pgsql.min.js",
        "es/languages/php-template.min.js",
        "es/languages/php.min.js",
        "es/languages/plaintext.min.js",
        "es/languages/pony.min.js",
        "es/languages/powershell.min.js",
        "es/languages/processing.min.js",
        "es/languages/profile.min.js",
        "es/languages/prolog.min.js",
        "es/languages/properties.min.js",
        "es/languages/protobuf.min.js",
        "es/languages/puppet.min.js",
        "es/languages/purebasic.min.js",
        "es/languages/python-repl.min.js",
        "es/languages/python.min.js",
        "es/languages/q.min.js",
        "es/languages/qml.min.js",
        "es/languages/r.min.js",
        "es/languages/reasonml.min.js",
        "es/languages/rib.min.js",
        "es/languages/roboconf.min.js",
        "es/languages/routeros.min.js",
        "es/languages/rsl.min.js",
        "es/languages/ruby.min.js",
        "es/languages/ruleslanguage.min.js",
        "es/languages/rust.min.js",
        "es/languages/sas.min.js",
        "es/languages/scala.min.js",
        "es/languages/scheme.min.js",
        "es/languages/scilab.min.js",
        "es/languages/scss.min.js",
        "es/languages/shell.min.js",
        "es/languages/smali.min.js",
        "es/languages/smalltalk.min.js",
        "es/languages/sml.min.js",
        "es/languages/sqf.min.js",
        "es/languages/sql.min.js",
        "es/languages/stan.min.js",
        "es/languages/stata.min.js",
        "es/languages/step21.min.js",
        "es/languages/stylus.min.js",
        "es/languages/subunit.min.js",
        "es/languages/swift.min.js",
        "es/languages/taggerscript.min.js",
        "es/languages/tap.min.js",
        "es/languages/tcl.min.js",
        "es/languages/thrift.min.js",
        "es/languages/tp.min.js",
        "es/languages/twig.min.js",
        "es/languages/typescript.min.js",
        "es/languages/vala.min.js",
        "es/languages/vbnet.min.js",
        "es/languages/vbscript-html.min.js",
        "es/languages/vbscript.min.js",
        "es/languages/verilog.min.js",
        "es/languages/vhdl.min.js",
        "es/languages/vim.min.js",
        "es/languages/wasm.min.js",
        "es/languages/wren.min.js",
        "es/languages/x86asm.min.js",
        "es/languages/xl.min.js",
        "es/languages/xml.min.js",
        "es/languages/xquery.min.js",
        "es/languages/yaml.min.js",
        "es/languages/zephir.min.js",
        "es/core.min.js",
        "es/highlight.min.js",
        "languages/1c.min.js",
        "languages/abnf.min.js",
        "languages/accesslog.min.js",
        "languages/actionscript.min.js",
        "languages/ada.min.js",
        "languages/angelscript.min.js",
        "languages/apache.min.js",
        "languages/applescript.min.js",
        "languages/arcade.min.js",
        "languages/arduino.min.js",
        "languages/armasm.min.js",
        "languages/asciidoc.min.js",
        "languages/aspectj.min.js",
        "languages/autohotkey.min.js",
        "languages/autoit.min.js",
        "languages/avrasm.min.js",
        "languages/awk.min.js",
        "languages/axapta.min.js",
        "languages/bash.min.js",
        "languages/basic.min.js",
        "languages/bnf.min.js",
        "languages/brainfuck.min.js",
        "languages/c.min.js",
        "languages/cal.min.js",
        "languages/capnproto.min.js",
        "languages/ceylon.min.js",
        "languages/clean.min.js",
        "languages/clojure-repl.min.js",
        "languages/clojure.min.js",
        "languages/cmake.min.js",
        "languages/coffeescript.min.js",
        "languages/coq.min.js",
        "languages/cos.min.js",
        "languages/cpp.min.js",
        "languages/crmsh.min.js",
        "languages/crystal.min.js",
        "languages/csharp.min.js",
        "languages/csp.min.js",
        "languages/css.min.js",
        "languages/d.min.js",
        "languages/dart.min.js",
        "languages/delphi.min.js",
        "languages/diff.min.js",
        "languages/django.min.js",
        "languages/dns.min.js",
        "languages/dockerfile.min.js",
        "languages/dos.min.js",
        "languages/dsconfig.min.js",
        "languages/dts.min.js",
        "languages/dust.min.js",
        "languages/ebnf.min.js",
        "languages/elixir.min.js",
        "languages/elm.min.js",
        "languages/erb.min.js",
        "languages/erlang-repl.min.js",
        "languages/erlang.min.js",
        "languages/excel.min.js",
        "languages/fix.min.js",
        "languages/flix.min.js",
        "languages/fortran.min.js",
        "languages/fsharp.min.js",
        "languages/gams.min.js",
        "languages/gauss.min.js",
        "languages/gcode.min.js",
        "languages/gherkin.min.js",
        "languages/glsl.min.js",
        "languages/gml.min.js",
        "languages/go.min.js",
        "languages/golo.min.js",
        "languages/gradle.min.js",
        "languages/graphql.min.js",
        "languages/groovy.min.js",
        "languages/haml.min.js",
        "languages/handlebars.min.js",
        "languages/haskell.min.js",
        "languages/haxe.min.js",
        "languages/hsp.min.js",
        "languages/http.min.js",
        "languages/hy.min.js",
        "languages/inform7.min.js",
        "languages/ini.min.js",
        "languages/irpf90.min.js",
        "languages/isbl.min.js",
        "languages/java.min.js",
        "languages/javascript.min.js",
        "languages/jboss-cli.min.js",
        "languages/json.min.js",
        "languages/julia-repl.min.js",
        "languages/julia.min.js",
        "languages/kotlin.min.js",
        "languages/lasso.min.js",
        "languages/latex.min.js",
        "languages/ldif.min.js",
        "languages/leaf.min.js",
        "languages/less.min.js",
        "languages/lisp.min.js",
        "languages/livecodeserver.min.js",
        "languages/livescript.min.js",
        "languages/llvm.min.js",
        "languages/lsl.min.js",
        "languages/lua.min.js",
        "languages/makefile.min.js",
        "languages/markdown.min.js",
        "languages/mathematica.min.js",
        "languages/matlab.min.js",
        "languages/maxima.min.js",
        "languages/mel.min.js",
        "languages/mercury.min.js",
        "languages/mipsasm.min.js",
        "languages/mizar.min.js",
        "languages/mojolicious.min.js",
        "languages/monkey.min.js",
        "languages/moonscript.min.js",
        "languages/n1ql.min.js",
        "languages/nestedtext.min.js",
        "languages/nginx.min.js",
        "languages/nim.min.js",
        "languages/nix.min.js",
        "languages/node-repl.min.js",
        "languages/nsis.min.js",
        "languages/objectivec.min.js",
        "languages/ocaml.min.js",
        "languages/openscad.min.js",
        "languages/oxygene.min.js",
        "languages/parser3.min.js",
        "languages/perl.min.js",
        "languages/pf.min.js",
        "languages/pgsql.min.js",
        "languages/php-template.min.js",
        "languages/php.min.js",
        "languages/plaintext.min.js",
        "languages/pony.min.js",
        "languages/powershell.min.js",
        "languages/processing.min.js",
        "languages/profile.min.js",
        "languages/prolog.min.js",
        "languages/properties.min.js",
        "languages/protobuf.min.js",
        "languages/puppet.min.js",
        "languages/purebasic.min.js",
        "languages/python-repl.min.js",
        "languages/python.min.js",
        "languages/q.min.js",
        "languages/qml.min.js",
        "languages/r.min.js",
        "languages/reasonml.min.js",
        "languages/rib.min.js",
        "languages/roboconf.min.js",
        "languages/routeros.min.js",
        "languages/rsl.min.js",
        "languages/ruby.min.js",
        "languages/ruleslanguage.min.js",
        "languages/rust.min.js",
        "languages/sas.min.js",
        "languages/scala.min.js",
        "languages/scheme.min.js",
        "languages/scilab.min.js",
        "languages/scss.min.js",
        "languages/shell.min.js",
        "languages/smali.min.js",
        "languages/smalltalk.min.js",
        "languages/sml.min.js",
        "languages/sqf.min.js",
        "languages/sql.min.js",
        "languages/stan.min.js",
        "languages/stata.min.js",
        "languages/step21.min.js",
        "languages/stylus.min.js",
        "languages/subunit.min.js",
        "languages/swift.min.js",
        "languages/taggerscript.min.js",
        "languages/tap.min.js",
        "languages/tcl.min.js",
        "languages/thrift.min.js",
        "languages/tp.min.js",
        "languages/twig.min.js",
        "languages/typescript.min.js",
        "languages/vala.min.js",
        "languages/vbnet.min.js",
        "languages/vbscript-html.min.js",
        "languages/vbscript.min.js",
        "languages/verilog.min.js",
        "languages/vhdl.min.js",
        "languages/vim.min.js",
        "languages/wasm.min.js",
        "languages/wren.min.js",
        "languages/x86asm.min.js",
        "languages/xl.min.js",
        "languages/xml.min.js",
        "languages/xquery.min.js",
        "languages/yaml.min.js",
        "languages/zephir.min.js",
        "styles/github-dark.min.css",
        "styles/github-dark.css"
      ]
    }
  ]
}